validator_collection_br/__init__.py
validator_collection_br/checkers_br.py
validator_collection_br/errors_br.py
validator_collection_br/validators_br.py
validator_collection_br-0.0.13.dist-info/DESCRIPTION.rst
validator_collection_br-0.0.13.dist-info/METADATA
validator_collection_br-0.0.13.dist-info/RECORD
validator_collection_br-0.0.13.dist-info/WHEEL
validator_collection_br-0.0.13.dist-info/metadata.json
validator_collection_br-0.0.13.dist-info/top_level.txt
